eleventools/__init__.py
eleventools/webhook_toolset.py
eleventools-0.1.3.dist-info/METADATA
eleventools-0.1.3.dist-info/WHEEL
eleventools-0.1.3.dist-info/licenses/LICENSE
eleventools-0.1.3.dist-info/RECORD
