Metadata-Version: 2.4
Name: eleventools
Version: 0.1.3
Summary: Use your Python functions as ElevenLabs agent tools
Project-URL: Homepage, https://github.com/Oleks-Y/eleventools
Project-URL: Repository, https://github.com/Oleks-Y/eleventools
Project-URL: Issues, https://github.com/Oleks-Y/eleventools/issues
Author-email: Oleks-Y <oleks.y@example.com>
License: MIT
License-File: LICENSE
Keywords: ai,elevenlabs,tools,webhooks
Classifier: Development Status :: 4 - Beta
Classifier: Intended Audience :: Developers
Classifier: License :: OSI Approved :: MIT License
Classifier: Operating System :: OS Independent
Classifier: Programming Language :: Python :: 3
Classifier: Programming Language :: Python :: 3.8
Classifier: Programming Language :: Python :: 3.9
Classifier: Programming Language :: Python :: 3.10
Classifier: Programming Language :: Python :: 3.11
Classifier: Programming Language :: Python :: 3.12
Classifier: Programming Language :: Python :: 3.13
Requires-Python: >=3.8
Requires-Dist: fastapi>=0.100.0
Requires-Dist: httpx>=0.24.0
Requires-Dist: uvicorn>=0.20.0
